CHANGELOG.txt
LICENSE.txt
MANIFEST.in
README.txt
setup.py
calculator/__init__.py
riekertsynapse.egg-info/PKG-INFO
riekertsynapse.egg-info/SOURCES.txt
riekertsynapse.egg-info/dependency_links.txt
riekertsynapse.egg-info/top_level.txt